strategy_tester/__init__.py
strategy_tester/backtest.py
strategy_tester/indicator.py
strategy_tester/strategy.py
strategy_tester/strategy_tester.py
strategy_tester/commands/__init__.py
strategy_tester/commands/calculator_trade.py
strategy_tester/encoder/__init__.py
strategy_tester/encoder/np_encoder.py
strategy_tester/handler/__init__.py
strategy_tester/handler/datahandler.py
strategy_tester/indicator/__init__.py
strategy_tester/indicator/indicator.py
strategy_tester/indicator/indicators_parallel.py
strategy_tester/models/__init__.py
strategy_tester/models/candle.py
strategy_tester/models/trade.py
strategy_tester/pandas_ta_supplementary_libraries/__init__.py
strategy_tester/pandas_ta_supplementary_libraries/chunks.py
strategy_tester/pandas_ta_supplementary_libraries/crossover.py
strategy_tester/pandas_ta_supplementary_libraries/crossunder.py
strategy_tester/pandas_ta_supplementary_libraries/highest.py
strategy_tester/pandas_ta_supplementary_libraries/lowest.py
strategy_tester/periodic/__init__.py
strategy_tester/periodic/periodic.py
strategy_tester/sheet/__init__.py
strategy_tester/sheet/sheet.py
strategy_tester-0.1.4.dist-info/LICENCE
strategy_tester-0.1.4.dist-info/METADATA
strategy_tester-0.1.4.dist-info/WHEEL
strategy_tester-0.1.4.dist-info/top_level.txt
strategy_tester-0.1.4.dist-info/RECORD
