Metadata-Version: 2.1
Name: strategy-tester
Version: 0.1.4
Summary: A python package for testing strategies
Home-page: UNKNOWN
Author: Ali Ardakani
Author-email: aliardakani78@gmail.com
License: UNKNOWN
Keywords: python,strategy,tester,trading,backtesting,performance
Platform: UNKNOWN
Classifier: Development Status :: 1 - Planning
Classifier: Intended Audience :: Developers
Classifier: Programming Language :: Python :: 3
Classifier: Operating System :: Unix
Classifier: Operating System :: MacOS :: MacOS X
Classifier: Operating System :: Microsoft :: Windows
License-File: LICENCE
Requires-Dist: aiohttp (==3.8.1)
Requires-Dist: aiosignal (==1.2.0)
Requires-Dist: async-timeout (==4.0.2)
Requires-Dist: attrs (==21.4.0)
Requires-Dist: certifi (==2021.10.8)
Requires-Dist: charset-normalizer (==2.0.12)
Requires-Dist: dateparser (==1.1.1)
Requires-Dist: frozenlist (==1.3.0)
Requires-Dist: idna (==3.3)
Requires-Dist: multidict (==6.0.2)
Requires-Dist: numpy (==1.22.3)
Requires-Dist: pandas (==1.4.2)
Requires-Dist: pandas-ta (==0.3.14b0)
Requires-Dist: python-binance (==1.0.15)
Requires-Dist: python-dateutil (==2.8.2)
Requires-Dist: pytz (==2022.1)
Requires-Dist: pytz-deprecation-shim (==0.1.0.post0)
Requires-Dist: regex (==2022.3.2)
Requires-Dist: requests (==2.27.1)
Requires-Dist: six (==1.16.0)
Requires-Dist: tzdata (==2022.1)
Requires-Dist: tzlocal (==4.2)
Requires-Dist: ujson (==5.1.0)
Requires-Dist: urllib3 (==1.26.9)
Requires-Dist: websockets (==9.1)
Requires-Dist: yarl (==1.7.2)
